LICENSE.txt
MANIFEST.in
README.md
setup.cfg
setup.py
creatFiles/__init__.py
creatFiles/creatFiles.pyd
creatFiles/function_refer.pyd
creatFiles/function_refer_ui.pyd
creatFiles.egg-info/PKG-INFO
creatFiles.egg-info/SOURCES.txt
creatFiles.egg-info/dependency_links.txt
creatFiles.egg-info/top_level.txt