Metadata-Version: 2.1
Name: creatFiles
Version: 0.1.5
Summary: 批量生成参见不适用文件
Home-page: https://alidocs.dingtalk.com/i/p/4oJRz0VRJyvmLZMydy0mV7WvjQn7MG89
Author: zhanghao
Author-email: 17891967090@163.com
Classifier: Programming Language :: Python
Requires-Python: >=3.8
License-File: LICENSE.txt
